ora_client/__init__.py
ora_client/admin.py
ora_client/executor.py
ora_client/job_definition.py
ora_client/job_type.py
ora_client/py.typed
ora_client/schedule_definition.py
ora_client/proto/__init__.py
ora_client/proto/descriptor_set.bin
ora_client/proto/ora/__init__.py
ora_client/proto/ora/common/__init__.py
ora_client/proto/ora/common/v1/__init__.py
ora_client/proto/ora/server/__init__.py
ora_client/proto/ora/server/v1/__init__.py
ora_client/proto/ora/snapshot/__init__.py
ora_client/proto/ora/snapshot/v1/__init__.py
ora_client-0.2.4.dist-info/METADATA
ora_client-0.2.4.dist-info/WHEEL
ora_client-0.2.4.dist-info/RECORD
