Metadata-Version: 2.4
Name: ora-client
Version: 0.2.4
Summary: Client library for the Ora scheduling system
Author-email: tamasfe <me@tamasfe.dev>
Requires-Python: >=3.12
Requires-Dist: betterproto>=2.0.0b7
Requires-Dist: loguru>=0.7.3
Requires-Dist: pydantic>=2.10.4
